{"stats":{"minecraft:mined":{"minecraft:wet_sponge":3,"minecraft:frosted_ice":3},"minecraft:used":{"minecraft:wet_sponge":1},"minecraft:custom":{"minecraft:jump":158,"minecraft:time_since_rest":4597,"minecraft:damage_taken":20,"minecraft:leave_game":4,"minecraft:time_since_death":4597,"minecraft:play_time":4597,"minecraft:sprint_one_cm":16913,"minecraft:walk_on_water_one_cm":1670,"minecraft:walk_one_cm":3914,"minecraft:sneak_time":15,"minecraft:total_world_time":4715,"minecraft:fall_one_cm":4878,"minecraft:fly_one_cm":111060},"minecraft:picked_up":{"minecraft:azure_bluet":1,"minecraft:wheat_seeds":30,"minecraft:dandelion":10,"minecraft:oxeye_daisy":1,"minecraft:wet_sponge":3}},"DataVersion":3839}